{"name":"Add Js Button","id":"salesforce;add-js-button","testSteps":[{"number":1,"description":"Given I navigate to the Login page","duration":10730,"startTime":"2019-11-13T10:18:28.272261200-06:00[America/Mexico_City]","screenshots":[{"screenshot":"3e6114ca01db12566d8ad549136bc600b38e3ac893b8d9546a70201ffdb93b5a.png","timeStamp":1573661919003}],"result":"SUCCESS","precondition":false,"level":0,"children":[{"number":2,"description":"Open login page","duration":10257,"startTime":"2019-11-13T10:18:28.730398500-06:00[America/Mexico_City]","screenshots":[{"screenshot":"3e6114ca01db12566d8ad549136bc600b38e3ac893b8d9546a70201ffdb93b5a.png","timeStamp":1573661918987}],"result":"SUCCESS","precondition":false,"level":1}]},{"number":3,"description":"When I submit the username and password","duration":6230,"startTime":"2019-11-13T10:18:39.004088600-06:00[America/Mexico_City]","screenshots":[{"screenshot":"68576f631eebcdb7f5f1dd0922e37effd485dad02a60ab6c05039e2000fbdd63.png","timeStamp":1573661925234}],"result":"SUCCESS","precondition":false,"level":0,"children":[{"number":4,"description":"Send login data","duration":6222,"startTime":"2019-11-13T10:18:39.009075900-06:00[America/Mexico_City]","screenshots":[{"screenshot":"68576f631eebcdb7f5f1dd0922e37effd485dad02a60ab6c05039e2000fbdd63.png","timeStamp":1573661925231}],"result":"SUCCESS","precondition":false,"level":1}]},{"number":5,"description":"Then I should Logged In","duration":12667,"startTime":"2019-11-13T10:18:45.234312500-06:00[America/Mexico_City]","screenshots":[{"screenshot":"6b2dd680b5977f313b94c33725326dde1a97d2732fa7d095aa5f0b161c4cc3dc.png","timeStamp":1573661937902}],"result":"SUCCESS","precondition":false,"level":0},{"number":6,"description":"Given I click on new Js Button","duration":1067,"startTime":"2019-11-13T10:18:57.902273900-06:00[America/Mexico_City]","screenshots":[{"screenshot":"5d7e7bece21d169ef277f9379566940d82558ae7f5e65cb917fcd3622504b626.png","timeStamp":1573661938969}],"result":"SUCCESS","precondition":false,"level":0},{"number":7,"description":"When I submit Js Button Informtion","duration":0,"startTime":"2019-11-13T10:18:58.969518700-06:00[America/Mexico_City]","screenshots":[{"screenshot":"5d7e7bece21d169ef277f9379566940d82558ae7f5e65cb917fcd3622504b626.png","timeStamp":1573661938971}],"precondition":false,"level":0}],"userStory":{"id":"salesforce","storyName":"salesforce","path":"src/test/resources/com/features/salesforce/jsbutton.feature","narrative":"  In order to test Home Page of application\n  As a Registered user\n  I want to validate the result of home page for Js Buttons\n\n  Description: Log in salesforce page","type":"feature"},"featureTag":{"name":"Salesforce/salesforce","type":"feature","displayName":"Salesforce/salesforce"},"title":"Add Js Button","backgroundTitle":"User Logged in","backgroundDescription":"","startTime":"2019-11-13T10:18:28.170534200-06:00[America/Mexico_City]","duration":0,"projectKey":"","manual":false,"testSource":"Cucumber","result":"SUCCESS"}